main.py
setup.py
bytebs.egg-info/PKG-INFO
bytebs.egg-info/SOURCES.txt
bytebs.egg-info/dependency_links.txt
bytebs.egg-info/requires.txt
bytebs.egg-info/top_level.txt